dttuong/__init__.py
dttuong/processing.py
dttuong-0.1.dist-info/METADATA
dttuong-0.1.dist-info/WHEEL
dttuong-0.1.dist-info/top_level.txt
dttuong-0.1.dist-info/RECORD
