Metadata-Version: 2.4
Name: dttuong
Version: 0.1
Summary: A library for learning and research purposes on image processing, performing piecewise linear transformations on grayscale and color images.
Home-page: https://github.com/tuong0706/dttuong
Author: Tuongne0706
Author-email: zzxr851@gmail.com
Classifier: Programming Language :: Python :: 3
Classifier: License :: OSI Approved :: MIT License
Classifier: Operating System :: OS Independent
Requires-Python: >=3.6
Requires-Dist: opencv-python
Requires-Dist: numpy
Requires-Dist: matplotlib
Requires-Dist: scikit-learn
Dynamic: author
Dynamic: author-email
Dynamic: classifier
Dynamic: description
Dynamic: description-content-type
Dynamic: home-page
Dynamic: requires-dist
Dynamic: requires-python
Dynamic: summary
